<?xml version="1.0" encoding="ISO-8859-1"?>
<metadata><Source>http://www.nbii.gov/metadata/mdata/FAO/fao_d_aquastat.sgml</Source>
<idinfo>
<citation>
<citeinfo>
<origin>Food and Agriculture Organization</origin>
<pubdate>2002</pubdate>
<title>Aquastat</title>
<geoform>maps data</geoform>
<pubinfo>
<pubplace>Rome, Italy</pubplace>
<publish>Food and Agriculture Organization</publish>
</pubinfo>
<onlink>http://www.fao.org/ag/agl/aglw/aquastat/dbase/index2.jsp</onlink>
</citeinfo>
</citation>
<descript>
<abstract>Aquastat is the Food and Agriculture Organization (FAO) global information system of water and agriculture developed by the Land and Water Development Division of FAO. Aquastat provides users with comprehensive information on the state of agricultural water management across the world, with emphasis on developing countries and countries in transition. Aquastat consists of a database which provides information on water and agriculture by countries organized by categories,  country profiles with standardized text by country and summary tables; maps and GIS with spatial data on water and irrigation. The most recent available information is given for land use, water resources, land under irrigation, source of irrigation water, irrigated crops and intensification, population, water use, irrigation technique, environment and drainage.</abstract>
<purpose>The purpose of Aquastat is to provide a clear picture of the situation of rural water resources management on a country basis, with emphasis on irrigation, and featuring major characteristics, trends, constraints and perspectives; to help support continental and regional analyses by providing systematic, up-to-date and reliable information on water for agriculture and rural development, and to serve as a tool for large-scale planning and forecasting.</purpose>
<supplinf>Information was obtained from http://www.fao.org/ag/agl/aglw/aquastat/main/index.htm  (previous geoform was 'Database')</supplinf>
</descript>
<timeperd>
<timeinfo>
<sngdate>
<caldate>2002</caldate>
</sngdate>
</timeinfo>
<current>publication date</current>
</timeperd>
<status>
<progress>In Work</progress>
<update>Continually</update>
</status>
<spdom>
<descgeog>Focuses on the countries of the world including developing countries and excluding Europe, the United States.</descgeog>
<bounding>
<westbc>-180</westbc>
<eastbc>180</eastbc>
<northbc>90</northbc>
<southbc>-90</southbc>
</bounding>
</spdom>
<keywords>
<theme>
<themekt>none</themekt>
<themekey>database</themekey>
<themekey>country profiles</themekey>
<themekey>maps</themekey>
<themekey>GIS</themekey>
<themekey>institutions</themekey>
<themekey>water resources</themekey>
<themekey>agricultural water use</themekey>
</theme>
<place>
<placekt>none</placekt>
<placekey>world</placekey>
<placekey>Afghanistan</placekey>
<placekey>Algeria</placekey>
<placekey>Angola</placekey>
<placekey>Antigua and Barbuda</placekey>
<placekey>Argentina</placekey>
<placekey>Armenia</placekey>
<placekey>Azerbaijan</placekey>
<placekey>Bahrain</placekey>
<placekey>Bangladesh</placekey>
<placekey>Barbados</placekey>
<placekey>Belarus</placekey>
<placekey>Belize</placekey>
<placekey>Benin</placekey>
<placekey>Bhutan</placekey>
<placekey>Bolivia</placekey>
<placekey>Botswana</placekey>
<placekey>Brazil</placekey>
<placekey>Brunei</placekey>
<placekey>Burkino Faso</placekey>
<placekey>Burundi</placekey>
<placekey>Cambodia</placekey>
<placekey>Cameroon</placekey>
<placekey>Cape Verde</placekey>
<placekey>Central African Republic</placekey>
<placekey>Chad</placekey>
<placekey>Chile</placekey>
<placekey>China</placekey>
<placekey>Colombia</placekey>
<placekey>Comoros</placekey>
<placekey>Congo</placekey>
<placekey>Costa Rica</placekey>
<placekey>Cote D'Ivoire</placekey>
<placekey>Cuba</placekey>
<placekey>Cyprus</placekey>
<placekey>Djibouti</placekey>
<placekey>Dominica</placekey>
<placekey>Ecuador</placekey>
<placekey>Egypt</placekey>
<placekey>El Salvador</placekey>
<placekey>Equitorial Guinea</placekey>
<placekey>Eritrea</placekey>
<placekey>Estonia</placekey>
<placekey>Ethipia</placekey>
<placekey>Gabon</placekey>
<placekey>Gambia</placekey>
<placekey>Georgia</placekey>
<placekey>Ghana</placekey>
<placekey>Grenada</placekey>
<placekey>Guatemala</placekey>
<placekey>Guinea</placekey>
<placekey>Guyana</placekey>
<placekey>Haiti</placekey>
<placekey>Honduras</placekey>
<placekey>India</placekey>
<placekey>Indonesia</placekey>
<placekey>Iran</placekey>
<placekey>Iraq</placekey>
<placekey>Jamaica</placekey>
<placekey>Japan</placekey>
<placekey>Jordan</placekey>
<placekey>Kazakhstan</placekey>
<placekey>Kenya</placekey>
<placekey>Korea</placekey>
<placekey>Kuwait</placekey>
<placekey>Kyrgyzstan</placekey>
<placekey>Laos</placekey>
<placekey>Latvia</placekey>
<placekey>Lebanon</placekey>
<placekey>Lesoto</placekey>
<placekey>Liberia</placekey>
<placekey>Lithuania</placekey>
<placekey>Madagascar</placekey>
<placekey>Malaui</placekey>
<placekey>Malaysia</placekey>
<placekey>Maldives</placekey>
<placekey>Mali</placekey>
<placekey>Malta</placekey>
<placekey>Mauritania</placekey>
<placekey>Mauritius</placekey>
<placekey>Mexico</placekey>
<placekey>Moldova</placekey>
<placekey>Mongolia</placekey>
<placekey>Morocco</placekey>
<placekey>Mozambique</placekey>
<placekey>Myanmar</placekey>
<placekey>Namibia</placekey>
<placekey>Nepal</placekey>
<placekey>Nicaragua</placekey>
<placekey>Niger</placekey>
<placekey>Nigeria</placekey>
<placekey>Oman</placekey>
<placekey>Pakistan</placekey>
<placekey>Panama</placekey>
<placekey>Papua New Guinea</placekey>
<placekey>Paraguay</placekey>
<placekey>Peru</placekey>
<placekey>Philippines</placekey>
<placekey>Qatar</placekey>
<placekey>Russian Federation</placekey>
<placekey>Rwanda</placekey>
<placekey>Saint Kitts</placekey>
<placekey>Nevis</placekey>
<placekey>Saint Lucia</placekey>
<placekey>Saint Vincent</placekey>
<placekey>Sao Tome and Principe</placekey>
<placekey>Saudi Arabia</placekey>
<placekey>Senegal</placekey>
<placekey>Seychelles</placekey>
<placekey>Sierra Leone</placekey>
<placekey>Somalia</placekey>
<placekey>South Africa</placekey>
<placekey>Sri Lanka</placekey>
<placekey>Sudan</placekey>
<placekey>Suriname</placekey>
<placekey>Swaziland</placekey>
<placekey>Syrian Arab Republic</placekey>
<placekey>Tajikistan</placekey>
<placekey>Tanzania</placekey>
<placekey>Thailand</placekey>
<placekey>Togo</placekey>
<placekey>Trinidad and Tobago</placekey>
<placekey>Tunisia</placekey>
<placekey>Turkmenistan</placekey>
<placekey>Uganda</placekey>
<placekey>Ukraine</placekey>
<placekey>United Arab Emirates</placekey>
<placekey>Uruguay</placekey>
<placekey>Uzbekistan</placekey>
<placekey>Venezuela</placekey>
<placekey>Viet Nam</placekey>
<placekey>Yemen</placekey>
<placekey>Zambia</placekey>
<placekey>Zimbabwe</placekey>
</place>
</keywords>
<accconst>none</accconst>
<useconst>none</useconst>
<ptcontac>
<cntinfo>
<cntorgp>
<cntorg>Food and Agriculture Organization</cntorg>
</cntorgp>
<cntaddr>
<addrtype>mailing and physical address</addrtype>
<address>Viale delle Terme di Caracalla, 00100</address>
<city>Rome</city>
<country>Italy</country>
</cntaddr>
<cntvoice>+39 06 5705 1</cntvoice>
<cntfax>+39 06 5705 3152</cntfax>
<cntemail>FAO-HQ@fao.org</cntemail>
<cntinst>Cable Address - FOODAGRI ROME</cntinst>
</cntinfo>
</ptcontac>
</idinfo>
<dataqual>
<logic>not applicable</logic>
<complete>Aquastat contains a wide range of information.  The completeness depends upon the specific component.  The database part of Aquastat provides the most recent available information, i.e. no time-series are yet available, for the following categories: population, water use, irrigation techniques, environment, drainage. The country profiles are based on the most recent information, which was available when the profile was written. They will be updated every five to ten years. For the most recent reliable data on water resources and their use in agriculture, reference is made to the Aquastat database. The country profiles are written for the countries listed in the keyword section of this report.  Maps and GIS feature, global maps of irrigated areas, global maps, a database on African dams, and African maps.  These may vary in completeness.</complete>
<lineage>
<procstep>
<procdesc>unknown</procdesc>
<procdate>Unknown</procdate>
</procstep>
</lineage>
</dataqual>
<spdoinfo>
<indspref>Based on local reference names</indspref>
</spdoinfo>
<eainfo>
<overview>
<eaover>Entity - freshwater availability; Attributes - database, country profiles, regional overviews, maps and GIS, institutions, water resources, agricultural water use, documents, links, glossary, land use, water resources, land under irrigation, source of irrigation water, irrigated crops and intensification,  population, water use, irrigation,  techniques, environment,  drainage</eaover>
<eadetcit>none</eadetcit>
</overview>
</eainfo>
<distinfo>
<distrib>
<cntinfo>
<cntorgp>
<cntorg>Food and Agriculture Organization</cntorg>
</cntorgp>
<cntaddr>
<addrtype>mailing and physical address</addrtype>
<address>Viale delle Terme di Caracalla, 00100</address>
<city>Rome</city>
<country>Italy</country>
</cntaddr>
<cntvoice>+39 06 5705 1</cntvoice>
<cntfax>+39 06 5705 3152</cntfax>
<cntemail>FAO-HQ@fao.org</cntemail>
<cntinst>Cable Address - FOODAGRI ROME</cntinst>
</cntinfo>
</distrib>
<distliab>Although these data have been processed successfully on a computer system at the Food and Agriculture Organization, no warranty expressed or implied is made regarding the accuracy or utility of the data on any other system or for general or scientific purposes, nor shall the act of distribution constitute any such warranty. This disclaimer applies both to individual use of the data and aggregate use with other data.  It is strongly recommended that these data are directly acquired from a Food and Agriculture Organization server, and not indirectly through other sources which may have changed the data in some way.  It is also strongly recommended that careful attention be paid to the contents of the metadata file associated with these data.  The Food and Agriculture Organization shall not be held liable for improper or incorrect use of the data described and/or contained herein.</distliab>
<stdorder>
<digform>
<digtinfo>
<formname>Excel or CSV</formname>
</digtinfo>
<digtopt>
<onlinopt>
<computer>
<networka>
<networkr>http://www.fao.org/ag/agl/aglw/aquastat/main/index.htm</networkr>
</networka>
</computer>
</onlinopt>
</digtopt>
</digform>
<fees>None, if available online.</fees>
</stdorder>
</distinfo>
<metainfo>
<metd>20011030</metd>
<metfrd>20021030</metfrd>
<metc>
<cntinfo>
<cntperp>
<cntper>Cheryl Solomon</cntper>
<cntorg>Science Systems and Applications, Inc.</cntorg>
</cntperp>
<cntpos>Metadata specialist</cntpos>
<cntaddr>
<addrtype>mailing and physical address</addrtype>
<address>10210 Greenbelt Road, Suite 500</address>
<city>Lanham</city>
<state>Maryland</state>
<postal>20706</postal>
</cntaddr>
<cntvoice>301 867-2080</cntvoice>
<cntfax>301-867-2149.</cntfax>
<cntemail>solomon@gcmd.nasa.gov</cntemail>
</cntinfo>
</metc>
<metstdn>FGDC Biological Data Profile of the Content Standard for Digital Geospatial Metadata</metstdn>
<metstdv>FGDC-STD-001.1-1999</metstdv>
</metainfo>
<mercury><begdate>20020101</begdate><enddate>20021231</enddate><htmlurl>http://mercury.ornl.gov/metadata/nbii/html/nbii/www.nbii.gov_metadata_mdata_FAO_fao_d_aquastat.html</htmlurl><LTER-Site>nbii</LTER-Site></mercury></metadata>
